.gitignore
Dockerfile
LICENSE
MANIFEST.in
README.md
docker-compose.yml
nginx.conf
requirements.txt
setup.py
uwsgi_params.par
data/README.md
data/bases/README.md
data/bases/generate_bases.sh
img/container.png
nginx/Dockerfile
scripts/prepare_instance.sh
singularity_tunel.egg-info/PKG-INFO
singularity_tunel.egg-info/SOURCES.txt
singularity_tunel.egg-info/dependency_links.txt
singularity_tunel.egg-info/entry_points.txt
singularity_tunel.egg-info/not-zip-safe
singularity_tunel.egg-info/requires.txt
singularity_tunel.egg-info/top_level.txt
tunel/__init__.py
tunel/api.py
tunel/auth.py
tunel/containers.py
tunel/logman.py
tunel/utils.py
tunel/version.py
tunel/views.py
tunel/static/css/bootstrap.min.css
tunel/static/css/datatables.min.css
tunel/static/css/fonts.min.css
tunel/static/css/generator.css
tunel/static/css/mobile-base-1.1.css
tunel/static/css/select2.min.css
tunel/static/css/skeleton.css
tunel/static/css/style.css
tunel/static/css/fonts/Montserrat-Black.eot
tunel/static/css/fonts/Montserrat-Black.svg
tunel/static/css/fonts/Montserrat-Black.ttf
tunel/static/css/fonts/Montserrat-Black.woff
tunel/static/css/fonts/Montserrat-Bold.eot
tunel/static/css/fonts/Montserrat-Bold.svg
tunel/static/css/fonts/Montserrat-Bold.ttf
tunel/static/css/fonts/Montserrat-Bold.woff
tunel/static/css/fonts/Montserrat-Light.eot
tunel/static/css/fonts/Montserrat-Light.svg
tunel/static/css/fonts/Montserrat-Light.ttf
tunel/static/css/fonts/Montserrat-Light.woff
tunel/static/css/fonts/Montserrat-Regular.eot
tunel/static/css/fonts/Montserrat-Regular.svg
tunel/static/css/fonts/Montserrat-Regular.ttf
tunel/static/css/fonts/Montserrat-Regular.woff
tunel/static/img/about-history.jpg
tunel/static/img/about-philosophy.jpg
tunel/static/img/about-visual.png
tunel/static/img/about-winners.jpg
tunel/static/img/contact-visual.png
tunel/static/img/introduction-visual.png
tunel/static/img/logo.png
tunel/static/img/robot.png
tunel/static/img/work-alex-nowak.jpg
tunel/static/img/work-metiew-smith.jpg
tunel/static/img/work-victory.jpg
tunel/static/js/bootstrap.min.js
tunel/static/js/datatables.min.js
tunel/static/js/generator-functions.js
tunel/static/js/jquery.min.js
tunel/static/js/select2.min.js
tunel/static/js/tipsy.js
tunel/storage/gdrive.py
tunel/templates/base.html
