Metadata-Version: 1.2
Name: singularity-tunel
Version: 1.0.0
Summary: commander and viewer to tunnel commands for HPC
Home-page: https://github.com/singularityhub/tunel
Author: Vanessa Sochat
Author-email: vsochat@users.noreply.github.com
Maintainer: Vanessa Sochat
Maintainer-email: vsochat@users.noreply.github.com
License: LICENSE
Keywords: commander,viewer,hpc,cluster,computing
Platform: UNKNOWN
Classifier: Intended Audience :: Science/Research
Classifier: Intended Audience :: Developers
Classifier: License :: OSI Approved :: MIT License
Classifier: Programming Language :: C
Classifier: Programming Language :: Python
Classifier: Topic :: Software Development
Classifier: Topic :: Scientific/Engineering
Classifier: Operating System :: Unix
Classifier: Programming Language :: Python :: 3
